Workbook

Sheet Overview
B2: Cryptocurrency Portfolio Analysis
B3: CodeAlpha Finance & Investment Analysis Internship — Task 2
B4: Assets: Bitcoin (BTC), Ethereum (ETH), Solana (SOL) | Data as of: September 7, 2026 | Currency: USD
B6: Asset | C6: Current Price ($) | D6: 52-Wk Low ($) | E6: 52-Wk High ($) | F6: Market Cap ($B) | G6: 1-Yr Return (%) | H6: 90-Day Realized Volatility (%) | I6: Risk Tier
B7: Bitcoin (BTC) | C7: 79700 | D7: 57832.5 | E7: 126186 | F7: 1580 | G7: -28 | H7: 41 | I7: Lower
B8: Ethereum (ETH) | C8: 2500 | D8: 1388.12 | E8: 4955.9 | F8: 305 | G8: -44 | H8: 60 | I8: Medium
B9: Solana (SOL) | C9: 104 | D9: 60.2 | E9: 253.38 | F9: 60.8 | G9: -55 | H9: 80 | I9: Higher
B11: Source: CoinDesk, CoinGecko, CoinMarketCap, Investing.com, DropStab research (accessed Sept 7-8, 2026). Returns and volatility are approximate, based on publicly available market data.

Sheet Risk Analysis
B2: Risk & Volatility Analysis
B4: Metric | C4: Bitcoin (BTC) | D4: Ethereum (ETH) | E4: Solana (SOL)
B5: 52-Wk Range Spread (proxy for volatility) | C5: =(Overview!E7-Overview!D7)/Overview!D7 -> 1.1819219 | D5: =(Overview!E8-Overview!D8)/Overview!D8 -> 2.5702245 | E5: =(Overview!E9-Overview!D9)/Overview!D9 -> 3.2089701
B6: 90-Day Realized Volatility (annualized-style, %) | C6: =Overview!H7 -> 41 | D6: =Overview!H8 -> 60 | E6: =Overview!H9 -> 80
B7: 1-Year Return (%) | C7: =Overview!G7 -> -28 | D7: =Overview!G8 -> -44 | E7: =Overview!G9 -> -55
B8: Risk Tier | C8: Lower (relative) | D8: Medium | E8: Higher
B9: Primary Role in Portfolio | C9: Store of value / 'digital gold', hedge vs. inflation | D9: Smart-contract platform, DeFi & tokenization infrastructure | E9: High-throughput L1, highest growth potential & drawdown risk
B11: Interpretation: Volatility rises with market cap size moving down the risk curve — BTC (largest, most institutionally held) is the least volatile of the three; SOL (smallest, most speculative) is the most volatile, per DropStab's Q3 2026 realized-volatility research (~41% BTC vs ~60% ETH vs ~80% SOL, 90-day realized).

Sheet Portfolio Simulation
B2: Hypothetical ₹1,00,000 Crypto Allocation — 1-Year Backtest
B3: Illustrative only — assumes investment made 1 year ago at then-prevailing prices, using approximate observed 1-year returns.
B5: Total Investment (₹) | C5: 100000
B6: USD/INR Exchange Rate (approx.) | C6: 88.5
B8: Asset | C8: Allocation (%) | D8: Amount Invested (₹) | E8: 1-Yr Return (%) | F8: Current Value (₹) | G8: Gain / (Loss) (₹)
B9: Bitcoin (BTC) | C9: 0.45 | D9: =$C$5*C9 -> 45000 | E9: =Overview!G7 -> -28 | F9: =D9*(1+E9/100) -> 32400 | G9: =F9-D9 -> -12600
B10: Ethereum (ETH) | C10: 0.3 | D10: =$C$5*C10 -> 30000 | E10: =Overview!G8 -> -44 | F10: =D10*(1+E10/100) -> 16800 | G10: =F10-D10 -> -13200
B11: Solana (SOL) | C11: 0.25 | D11: =$C$5*C11 -> 25000 | E11: =Overview!G9 -> -55 | F11: =D11*(1+E11/100) -> 11250 | G11: =F11-D11 -> -13750
B12: TOTAL | C12: =SUM(C9:C11) -> 1 | D12: =SUM(D9:D11) -> 100000 | F12: =SUM(F9:F11) -> 60450 | G12: =SUM(G9:G11) -> -39550
B14: Overall Portfolio Return (%) | C14: =G12/D12 -> -0.3955
B16: Note: Change the allocation % (blue cells) or total investment amount to model a different mix. Formulas recalculate automatically.

Sheet Insights & Recommendations
B2: Insights & Recommendations
B4: Diversification benefit
B5: Combining BTC, ETH and SOL spans three distinct risk/return profiles — a conservative 'store of value' anchor, a mid-risk platform play, and a high-beta growth bet — rather than three correlated bets on the same theme.
B7: Risk-adjusted positioning
B8: Bitcoin's lower relative volatility (~41% realized) and largest market cap make it suited as the 'core' holding; Solana's higher volatility (~80%) suggests it should be sized as a smaller, higher-conviction 'satellite' position.
B10: All three de-rated over 12 months
B11: Despite strong fundamentals-side news (ETF approvals, network upgrades, institutional treasuries), all three assets are down over the trailing year, reflecting a broad 2026 crypto market correction rather than asset-specific weakness.
B13: Suggested allocation logic
B14: A 45% BTC / 30% ETH / 25% SOL split (as modelled in the Portfolio Simulation tab) tilts toward capital preservation while retaining meaningful upside exposure — investors with higher risk tolerance could shift weight toward ETH/SOL, and more conservative investors could raise the BTC weight further.
B16: Key monitorables going forward
B17: US Fed rate policy and spot-ETF flows (all three), Ethereum's Layer-2 scaling roadmap, and Solana's Alpenglow upgrade (targeting ~150ms finality, rolling out through Q4 2026).
B20: Disclaimer: This analysis is prepared for educational purposes as part of the CodeAlpha internship and does not constitute investment advice. Cryptocurrency investments carry substantial risk of loss. Verify current prices before making any decisions.
